LICENSE
README.md
setup.py
./easymms/__init__.py
./easymms/_logger.py
./easymms/constants.py
./easymms/utils.py
./easymms/models/__init__.py
./easymms/models/alignment.py
./easymms/models/asr.py
./easymms/models/tts.py
./tests/__init__.py
./tests/test_asr.py
./tests/test_tts.py
easymms.egg-info/PKG-INFO
easymms.egg-info/SOURCES.txt
easymms.egg-info/dependency_links.txt
easymms.egg-info/not-zip-safe
easymms.egg-info/requires.txt
easymms.egg-info/top_level.txt
tests/test_asr.py
tests/test_tts.py