Metadata-Version: 2.1
Name: easymms
Version: 0.1.6
Summary: A simple Python package to easily use Meta's Massively Multilingual Speech (MMS) project
Author: Abdeladim Sadiki
License: MIT
Project-URL: Documentation, https://abdeladim-s.github.io/easymms/
Project-URL: Source, https://abdeladim-s.github.io/easymms/
Project-URL: Tracker, https://abdeladim-s.github.io/easymms/issues
Requires-Python: >=3.8
License-File: LICENSE
